{"spaces": [{"author": "zamburu1", "authorData": {"_id": "67b21eccf745d44676cad7ae", "avatarUrl": "/avatars/b34b6cf5e3aba72b7ccbd08dfccd8da2.svg", "fullname": "zambu", "name": "zamburu1", "type": "user", "isPro": false, "isHf": false, "isHfAdmin": false, "isMod": false}, "colorFrom": "indigo", "colorTo": "yellow", "createdAt": "2025-05-31T02:40:21.000Z", "emoji": "🌖", "id": "zamburu1/hero", "lastModified": "2025-05-31T02:41:12.000Z", "likes": 0, "pinned": false, "private": false, "sdk": "docker", "repoType": "space", "runtime": {"stage": "RUNNING", "hardware": {"current": "cpu-basic", "requested": "cpu-basic"}, "storage": null, "gcTimeout": 172800, "errorMessage": null, "replicas": {"requested": 1}, "devMode": false, "domains": [{"domain": "zamburu1-hero.hf.space", "stage": "READY"}]}, "title": "Hero", "isLikedByUser": false, "trendingScore": 0}, {"author": "asterll", "authorData": {"_id": "6839b3d5a2d6f83cf14d443b", "avatarUrl": "https://cdn-avatars.huggingface.co/v1/production/uploads/no-auth/Xq43A-5pixlDeKtOImlpC.png", "fullname": "eve", "name": "asterll", "type": "user", "isPro": false, "isHf": false, "isHfAdmin": false, "isMod": false}, "colorFrom": "indigo", "colorTo": "blue", "createdAt": "2025-05-31T02:40:19.000Z", "emoji": "📊", "id": "asterll/ws", "lastModified": "2025-05-31T02:41:53.000Z", "likes": 0, "pinned": false, "private": false, "sdk": "docker", "repoType": "space", "runtime": {"stage": "BUILDING", "hardware": {"current": null, "requested": "cpu-basic"}, "storage": null, "gcTimeout": 172800, "replicas": {"requested": 1}, "abuse": {"flaggedAt": "2025-05-31T02:41:15.486Z", "detector": "RepoScanner", "reason": "[Dockerfile] TOR Client"}, "devMode": false, "domains": [{"domain": "asterll-ws.hf.space", "stage": "READY"}]}, "title": "Ws", "isLikedByUser": false, "trendingScore": 0}, {"author": "Suburst", "authorData": {"_id": "65cb3085ac07b2595bd894d5", "avatarUrl": "https://cdn-avatars.huggingface.co/v1/production/uploads/noauth/kg0jGtu-nsk71oDkjlpH4.jpeg", "fullname": "Suburst", "name": "Suburst", "type": "user", "isPro": false, "isHf": false, "isHfAdmin": false, "isMod": false, "followerCount": 2}, "colorFrom": "indigo", "colorTo": "purple", "createdAt": "2025-05-31T02:35:48.000Z", "emoji": "🏃", "id": "Suburst/NJU_Final_Transformer_Tanslation", "lastModified": "2025-05-31T02:37:17.000Z", "likes": 0, "pinned": false, "private": false, "sdk": "gradio", "repoType": "space", "runtime": {"stage": "RUNTIME_ERROR", "hardware": {"current": null, "requested": "cpu-basic"}, "storage": null, "gcTimeout": 172800, "errorMessage": "Exit code: 1. Reason: Traceback (most recent call last):\n  File \"/home/user/app/app.py\", line 3, in <module>\n    from loguru import logger\nModuleNotFoundError: No module named 'loguru'\n", "replicas": {"requested": 1}, "devMode": false, "domains": [{"domain": "suburst-nju-final-transformer-tanslation.hf.space", "stage": "READY"}]}, "shortDescription": "南京大学智科 NLP小作业", "title": "NJU Final Transformer Tanslation", "isLikedByUser": false, "trendingScore": 0}, {"author": "kunyee", "authorData": {"_id": "680c3a3f0bfc06160b2e0916", "avatarUrl": "/avatars/3d3cbdc519d66f225aaf34f17e5a413b.svg", "fullname": "kunyee Kim", "name": "kunyee", "type": "user", "isPro": false, "isHf": false, "isHfAdmin": false, "isMod": false}, "colorFrom": "red", "colorTo": "red", "createdAt": "2025-05-31T02:32:02.000Z", "emoji": "🚀", "id": "kunyee/aitutor", "lastModified": "2025-05-31T02:42:47.000Z", "likes": 0, "pinned": false, "private": false, "sdk": "docker", "repoType": "space", "runtime": {"stage": "BUILDING", "hardware": {"current": null, "requested": "cpu-basic"}, "storage": null, "gcTimeout": 172800, "replicas": {"requested": 1}, "devMode": false, "domains": [{"domain": "kunyee-aitutor.hf.space", "stage": "READY"}]}, "shortDescription": "Streamlit template space", "title": "Aitutor", "isLikedByUser": false, "trendingScore": 0}, {"author": "SONGHOOW", "authorData": {"_id": "680c3b2978e732e714cf8c02", "avatarUrl": "/avatars/f4153c7fbd42a388f2ef70399d52777f.svg", "fullname": "SUNGHOMOON", "name": "SONGHOOW", "type": "user", "isPro": false, "isHf": false, "isHfAdmin": false, "isMod": false}, "colorFrom": "red", "colorTo": "red", "createdAt": "2025-05-31T02:31:58.000Z", "emoji": "🚀", "id": "SONGHOOW/aiTutor", "lastModified": "2025-05-31T02:42:59.000Z", "likes": 0, "pinned": false, "private": false, "sdk": "docker", "repoType": "space", "runtime": {"stage": "BUILDING", "hardware": {"current": null, "requested": "cpu-basic"}, "storage": null, "gcTimeout": 172800, "replicas": {"requested": 1}, "devMode": false, "domains": [{"domain": "songhoow-aitutor.hf.space", "stage": "READY"}]}, "shortDescription": "Streamlit template space", "title": "AiTutor", "isLikedByUser": false, "trendingScore": 0}, {"author": "doh2842", "authorData": {"_id": "680c3a32d27b417e49e2c13c", "avatarUrl": "/avatars/a98745f054eee09c34a8dc6d67cd21d3.svg", "fullname": "dohyun", "name": "doh2842", "type": "user", "isPro": false, "isHf": false, "isHfAdmin": false, "isMod": false}, "colorFrom": "red", "colorTo": "red", "createdAt": "2025-05-31T02:31:28.000Z", "emoji": "🚀", "id": "doh2842/aiTutor", "lastModified": "2025-05-31T02:41:59.000Z", "likes": 0, "pinned": false, "private": false, "sdk": "docker", "repoType": "space", "runtime": {"stage": "BUILD_ERROR", "hardware": {"current": null, "requested": "cpu-basic"}, "storage": null, "gcTimeout": 172800, "errorMessage": "Job failed with exit code: 1", "replicas": {"requested": 1}, "devMode": false, "domains": [{"domain": "doh2842-aitutor.hf.space", "stage": "READY"}]}, "shortDescription": "Streamlit template space", "title": "AiTutor", "isLikedByUser": false, "trendingScore": 0}, {"author": "10805j", "authorData": {"_id": "67e74d0e05d7355e4753b057", "avatarUrl": "/avatars/70d1532dbb7f91a638a60ece121e6c29.svg", "fullname": "sy", "name": "10805j", "type": "user", "isPro": false, "isHf": false, "isHfAdmin": false, "isMod": false}, "colorFrom": "red", "colorTo": "red", "createdAt": "2025-05-31T02:31:14.000Z", "emoji": "🚀", "id": "10805j/aitutor", "lastModified": "2025-05-31T02:40:46.000Z", "likes": 1, "pinned": false, "private": false, "sdk": "docker", "repoType": "space", "runtime": {"stage": "BUILD_ERROR", "hardware": {"current": null, "requested": "cpu-basic"}, "storage": null, "gcTimeout": 172800, "errorMessage": "Job failed with exit code: 1", "replicas": {"requested": 1}, "devMode": false, "domains": [{"domain": "10805j-aitutor.hf.space", "stage": "READY"}]}, "shortDescription": "Streamlit template space", "title": "Aitutor", "isLikedByUser": false, "trendingScore": 1}, {"author": "mompirry", "authorData": {"_id": "641f731bf8c8b04c0babe030", "avatarUrl": "/avatars/6b21080e2808468ac785d4441449b159.svg", "fullname": "meier", "name": "mompirry", "type": "user", "isPro": false, "isHf": false, "isHfAdmin": false, "isMod": false}, "colorFrom": "green", "colorTo": "purple", "createdAt": "2025-05-31T02:31:11.000Z", "emoji": "⚡", "id": "mompirry/soso", "lastModified": "2025-05-31T02:31:39.000Z", "likes": 0, "pinned": false, "private": false, "sdk": "docker", "repoType": "space", "runtime": {"stage": "RUNNING", "hardware": {"current": "cpu-basic", "requested": "cpu-basic"}, "storage": null, "gcTimeout": 172800, "replicas": {"current": 1, "requested": 1}, "devMode": false, "domains": [{"domain": "mompirry-soso.hf.space", "stage": "READY"}], "sha": "6365e9fee1805400be7898106257068eff9835c6"}, "title": "Soso", "isLikedByUser": false, "trendingScore": 0}, {"author": "srikanth421", "authorData": {"_id": "642631f0c71d90951ea5703e", "avatarUrl": "/avatars/1ee7d66b77aa2e5f632069f2620bc028.svg", "fullname": "Srikanth Potukuchi", "name": "srikanth421", "type": "user", "isPro": false, "isHf": false, "isHfAdmin": false, "isMod": false}, "colorFrom": "green", "colorTo": "purple", "createdAt": "2025-05-31T02:31:05.000Z", "emoji": "🌖", "id": "srikanth421/RentalPricePredictionBackend", "lastModified": "2025-05-31T02:39:39.000Z", "likes": 0, "pinned": false, "private": false, "sdk": "docker", "repoType": "space", "runtime": {"stage": "APP_STARTING", "hardware": {"current": null, "requested": "cpu-basic"}, "storage": null, "gcTimeout": 172800, "replicas": {"requested": 1}, "devMode": false, "domains": [{"domain": "srikanth421-rentalpricepredictionbackend.hf.space", "stage": "READY"}]}, "title": "RentalPricePredictionBackend", "isLikedByUser": false, "trendingScore": 0}, {"author": "vzxweh", "authorData": {"_id": "67e74cec3745a0c5dd8e92f8", "avatarUrl": "/avatars/fd7f0b7e176dd5fe3eef5ca89cbf6597.svg", "fullname": "dayul", "name": "vzxweh", "type": "user", "isPro": false, "isHf": false, "isHfAdmin": false, "isMod": false}, "colorFrom": "red", "colorTo": "red", "createdAt": "2025-05-31T02:29:45.000Z", "emoji": "🚀", "id": "vzxweh/aiTutor", "lastModified": "2025-05-31T02:42:26.000Z", "likes": 0, "pinned": false, "private": false, "sdk": "docker", "repoType": "space", "runtime": {"stage": "BUILD_ERROR", "hardware": {"current": null, "requested": "cpu-basic"}, "storage": null, "gcTimeout": 172800, "errorMessage": "Job failed with exit code: 1", "replicas": {"requested": 1}, "devMode": false, "domains": [{"domain": "vzxweh-aitutor.hf.space", "stage": "READY"}]}, "shortDescription": "Streamlit template space", "title": "AiTutor", "isLikedByUser": false, "trendingScore": 0}, {"author": "daqc", "authorData": {"_id": "64461026e1fd8d65b27e6187", "avatarUrl": "https://cdn-avatars.huggingface.co/v1/production/uploads/64461026e1fd8d65b27e6187/i6UH81YW86iMpg9kkMdPG.jpeg", "fullname": "David Quispe", "name": "daqc", "type": "user", "isPro": true, "isHf": false, "isHfAdmin": false, "isMod": false, "followerCount": 18}, "colorFrom": "yellow", "colorTo": "purple", "createdAt": "2025-05-31T02:26:21.000Z", "emoji": "💬", "id": "daqc/Gradio", "lastModified": "2025-05-31T02:26:23.000Z", "likes": 0, "pinned": false, "private": false, "sdk": "gradio", "repoType": "space", "runtime": {"stage": "RUNNING", "hardware": {"current": "cpu-basic", "requested": "cpu-basic"}, "storage": null, "gcTimeout": 172800, "replicas": {"current": 1, "requested": 1}, "devMode": false, "domains": [{"domain": "daqc-gradio.hf.space", "stage": "READY"}], "sha": "d4177d1d2e3c347eb98a17339df9df161a34aa97"}, "title": "Gradio", "isLikedByUser": false, "trendingScore": 0}, {"author": "sionhan", "authorData": {"_id": "680c3a73ddb4267436ba4016", "avatarUrl": "https://cdn-avatars.huggingface.co/v1/production/uploads/no-auth/29DGjhitK3y41iUgQ-feA.png", "fullname": "sion", "name": "sionhan", "type": "user", "isPro": false, "isHf": false, "isHfAdmin": false, "isMod": false}, "colorFrom": "red", "colorTo": "red", "createdAt": "2025-05-31T02:26:17.000Z", "emoji": "🚀", "id": "sionhan/ai_tutor", "lastModified": "2025-05-31T02:36:40.000Z", "likes": 0, "pinned": false, "private": false, "sdk": "docker", "repoType": "space", "runtime": {"stage": "BUILD_ERROR", "hardware": {"current": null, "requested": "cpu-basic"}, "storage": null, "gcTimeout": 172800, "errorMessage": "Job failed with exit code: 1", "replicas": {"requested": 1}, "devMode": false, "domains": [{"domain": "sionhan-ai-tutor.hf.space", "stage": "READY"}]}, "shortDescription": "Streamlit template space", "title": "Ai Tutor", "isLikedByUser": false, "trendingScore": 0}, {"author": "poorna-prog", "authorData": {"_id": "683a6681466ab6a71b778ad8", "avatarUrl": "https://cdn-avatars.huggingface.co/v1/production/uploads/no-auth/Xd-ZG8nolUw7gqo8ggZ4n.png", "fullname": "Poorna Chandra. M", "name": "poorna-prog", "type": "user", "isPro": false, "isHf": false, "isHfAdmin": false, "isMod": false}, "colorFrom": "red", "colorTo": "red", "createdAt": "2025-05-31T02:25:16.000Z", "emoji": "🚀", "id": "poorna-prog/chatai", "lastModified": "2025-05-31T02:25:22.000Z", "likes": 0, "pinned": false, "private": false, "sdk": "docker", "repoType": "space", "runtime": {"stage": "RUNNING", "hardware": {"current": "cpu-basic", "requested": "cpu-basic"}, "storage": null, "gcTimeout": 172800, "replicas": {"current": 1, "requested": 1}, "devMode": false, "domains": [{"domain": "poorna-prog-chatai.hf.space", "stage": "READY"}], "sha": "ac351881ce3db075a30ed11ac925ee138d8eb6a0"}, "shortDescription": "Streamlit template space", "title": "Chatai", "isLikedByUser": false, "trendingScore": 0}, {"author": "makhtar7186", "authorData": {"_id": "675399f511d9221e28796801", "avatarUrl": "/avatars/da179eb2287c6b23ccd9491ac9760d5d.svg", "fullname": "Makhtar Faye", "name": "makhtar7186", "type": "user", "isPro": false, "isHf": false, "isHfAdmin": false, "isMod": false, "followerCount": 1}, "colorFrom": "blue", "colorTo": "indigo", "createdAt": "2025-05-31T02:23:55.000Z", "emoji": "📚", "id": "makhtar7186/telegram_medicalBot", "lastModified": "2025-05-31T02:39:38.000Z", "likes": 0, "pinned": false, "private": false, "sdk": "docker", "repoType": "space", "runtime": {"stage": "APP_STARTING", "hardware": {"current": null, "requested": "cpu-basic"}, "storage": null, "gcTimeout": 172800, "replicas": {"requested": 1}, "devMode": false, "domains": [{"domain": "makhtar7186-telegram-medicalbot.hf.space", "stage": "READY"}]}, "title": "Telegram MedicalBot", "isLikedByUser": false, "trendingScore": 0}, {"author": "loudio", "authorData": {"_id": "68390cd977cf53d709e03c08", "avatarUrl": "/avatars/4f77037a756d91d3646e9d80a3391c88.svg", "fullname": "T A", "name": "loudio", "type": "user", "isPro": false, "isHf": false, "isHfAdmin": false, "isMod": false}, "colorFrom": "yellow", "colorTo": "purple", "createdAt": "2025-05-31T02:22:35.000Z", "emoji": "💬", "id": "loudio/SEO-workflow-automation", "lastModified": "2025-05-30T02:10:22.000Z", "likes": 0, "pinned": false, "private": false, "sdk": "gradio", "repoType": "space", "runtime": {"stage": "RUNNING", "hardware": {"current": "cpu-basic", "requested": "cpu-basic"}, "storage": null, "gcTimeout": 172800, "replicas": {"current": 1, "requested": 1}, "devMode": false, "domains": [{"domain": "loudio-seo-workflow-automation.hf.space", "stage": "READY"}], "sha": "2a951156aa3a37eca86bcd1e322b68dadcdd56cf"}, "title": "Textgen V8", "isLikedByUser": false, "originSpace": {"name": "loudio/textgen_v8", "author": {"_id": "68390cd977cf53d709e03c08", "avatarUrl": "/avatars/4f77037a756d91d3646e9d80a3391c88.svg", "fullname": "T A", "name": "loudio", "type": "user", "isPro": false, "isHf": false, "isHfAdmin": false, "isMod": false}}, "trendingScore": 0}, {"author": "consteve77", "authorData": {"_id": "6749d88732cc5ff1e4c9c74b", "avatarUrl": "https://cdn-avatars.huggingface.co/v1/production/uploads/no-auth/O88gwbea8KzZUn4Kkd5wa.png", "fullname": "Abdurahmonov Sayidmurod", "name": "consteve77", "type": "user", "isPro": false, "isHf": false, "isHfAdmin": false, "isMod": false}, "colorFrom": "blue", "colorTo": "green", "createdAt": "2025-05-31T02:22:16.000Z", "emoji": "👁", "id": "consteve77/gptdemo", "lastModified": "2025-05-31T02:36:52.000Z", "likes": 0, "pinned": false, "private": false, "sdk": "gradio", "repoType": "space", "runtime": {"stage": "RUNTIME_ERROR", "hardware": {"current": null, "requested": "cpu-basic"}, "storage": null, "gcTimeout": 172800, "errorMessage": "Exit code: 0. Reason: application does not seem to be initialized", "replicas": {"requested": 1}, "devMode": false, "domains": [{"domain": "consteve77-gptdemo.hf.space", "stage": "READY"}]}, "shortDescription": "It's a Gradio app", "title": "Gptdemo", "isLikedByUser": false, "trendingScore": 0}, {"author": "thedatag", "authorData": {"_id": "65c2760f749cfed07446faf4", "avatarUrl": "/avatars/fa4ea0922b2f7ae1116845f06e199b6a.svg", "fullname": "Haidar Bin Hamid", "name": "thedatag", "type": "user", "isPro": false, "isHf": false, "isHfAdmin": false, "isMod": false}, "colorFrom": "red", "colorTo": "red", "createdAt": "2025-05-31T02:20:07.000Z", "emoji": "🚀", "id": "thedatag/DevineAsk", "lastModified": "2025-05-31T02:20:08.000Z", "likes": 0, "pinned": false, "private": false, "sdk": "docker", "repoType": "space", "runtime": {"stage": "RUNNING", "hardware": {"current": "cpu-basic", "requested": "cpu-basic"}, "storage": null, "gcTimeout": 172800, "replicas": {"current": 1, "requested": 1}, "devMode": false, "domains": [{"domain": "thedatag-devineask.hf.space", "stage": "READY"}], "sha": "8fc00b4d5c4ae4c9db5602b5a149713930785819"}, "shortDescription": "References the Bible, Quran, and Torah to answer questions", "title": "DevineAsk", "isLikedByUser": false, "trendingScore": 0}, {"author": "suprimedev", "authorData": {"_id": "6520838d2d3ba46ccdd5f7df", "avatarUrl": "/avatars/35f859bb6aae78af159f6c05b69f9b45.svg", "fullname": "Seyed ali hashemi", "name": "suprimedev", "type": "user", "isPro": false, "isHf": false, "isHfAdmin": false, "isMod": false, "followerCount": 2}, "colorFrom": "red", "colorTo": "gray", "createdAt": "2025-05-31T02:20:03.000Z", "emoji": "📊", "id": "suprimedev/Persian-TTS-talkbot", "lastModified": "2025-02-15T12:05:23.000Z", "likes": 0, "pinned": false, "private": false, "sdk": "gradio", "repoType": "space", "runtime": {"stage": "RUNNING", "hardware": {"current": "cpu-basic", "requested": "cpu-basic"}, "storage": null, "gcTimeout": 172800, "replicas": {"current": 1, "requested": 1}, "devMode": false, "domains": [{"domain": "suprimedev-persian-tts-talkbot.hf.space", "stage": "READY"}], "sha": "e51464f76f8e28d0343ca8bd294dce174cf2d756"}, "shortDescription": "Inference of Persian TTS models using sherpa-onnx", "title": "Persian TTS Sherpa", "isLikedByUser": false, "originSpace": {"name": "karim23657/Persian-TTS-sherpa", "author": {"_id": "64db477069d21c567be9056a", "avatarUrl": "https://cdn-avatars.huggingface.co/v1/production/uploads/noauth/0dChB0S8vsC1wHuxWMmEL.jpeg", "fullname": "K M H S", "name": "karim23657", "type": "user", "isPro": false, "isHf": false, "isHfAdmin": false, "isMod": false, "followerCount": 17}}, "trendingScore": 0}, {"author": "C6web3", "authorData": {"_id": "683a64c800c48087d3073eeb", "avatarUrl": "https://cdn-avatars.huggingface.co/v1/production/uploads/no-auth/hlNX3jOlewjLjmMliTorw.png", "fullname": "C6web3", "name": "C6web3", "type": "user", "isPro": false, "isHf": false, "isHfAdmin": false, "isMod": false}, "colorFrom": "green", "colorTo": "pink", "createdAt": "2025-05-31T02:18:46.000Z", "emoji": "⚡⚡⚡", "id": "C6web3/ain8n", "lastModified": "2025-04-15T07:48:17.000Z", "likes": 0, "pinned": false, "private": false, "sdk": "docker", "repoType": "space", "runtime": {"stage": "RUNNING", "hardware": {"current": "cpu-basic", "requested": "cpu-basic"}, "storage": null, "gcTimeout": 172800, "replicas": {"current": 1, "requested": 1}, "devMode": false, "domains": [{"domain": "c6web3-ain8n.hf.space", "stage": "READY"}], "sha": "0abcf01dafce551d0ff2260b86ae855473dc8fe3"}, "title": "ai + n8n", "isLikedByUser": false, "originSpace": {"name": "fuliai/ain8n", "author": {"_id": "66c2aee47d1b24912106154a", "avatarUrl": "https://cdn-avatars.huggingface.co/v1/production/uploads/66c2aee47d1b24912106154a/z3qnPj8O6XnSUFhQrDlqH.jpeg", "fullname": "aigem", "name": "fuliai", "type": "user", "isPro": false, "isHf": false, "isHfAdmin": false, "isMod": false, "followerCount": 24}}, "trendingScore": 0}, {"author": "sanosk", "authorData": {"_id": "67a5e8d4c4829a54b5e90638", "avatarUrl": "https://cdn-avatars.huggingface.co/v1/production/uploads/no-auth/nYyrW0yIhyTJJlvzDiPoC.png", "fullname": "Raju Tandukar", "name": "sanosk", "type": "user", "isPro": false, "isHf": false, "isHfAdmin": false, "isMod": false}, "colorFrom": "pink", "colorTo": "yellow", "createdAt": "2025-05-31T02:18:18.000Z", "emoji": "⚡", "id": "sanosk/First_agent_template", "lastModified": "2025-05-06T08:19:21.000Z", "likes": 0, "pinned": false, "private": false, "sdk": "gradio", "repoType": "space", "runtime": {"stage": "RUNNING", "hardware": {"current": "cpu-basic", "requested": "cpu-basic"}, "storage": null, "gcTimeout": 172800, "replicas": {"current": 1, "requested": 1}, "devMode": false, "domains": [{"domain": "sanosk-first-agent-template.hf.space", "stage": "READY"}], "sha": "8c5c24b6f1ed08e7fd34a59f44e854580def9101"}, "title": "First Agent Template", "isLikedByUser": false, "originSpace": {"name": "agents-course/First_agent_template", "author": {"avatarUrl": "https://cdn-avatars.huggingface.co/v1/production/uploads/60cae820b1c79a3e4b436664/gSOeYxuhnE0U0HFeh__wA.png", "fullname": "Hugging Face Agents Course", "name": "agents-course", "type": "org", "isHf": false, "isHfAdmin": false, "isMod": false, "isEnterprise": true, "followerCount": 36820}}, "trendingScore": 0}, {"author": "consteve77", "authorData": {"_id": "6749d88732cc5ff1e4c9c74b", "avatarUrl": "https://cdn-avatars.huggingface.co/v1/production/uploads/no-auth/O88gwbea8KzZUn4Kkd5wa.png", "fullname": "Abdurahmonov Sayidmurod", "name": "consteve77", "type": "user", "isPro": false, "isHf": false, "isHfAdmin": false, "isMod": false}, "colorFrom": "gray", "colorTo": "indigo", "createdAt": "2025-05-31T02:15:40.000Z", "emoji": "🌍", "id": "consteve77/gpt_analysis2", "lastModified": "2025-05-31T02:17:15.000Z", "likes": 0, "pinned": false, "private": false, "sdk": "gradio", "repoType": "space", "runtime": {"stage": "RUNTIME_ERROR", "hardware": {"current": null, "requested": "cpu-basic"}, "storage": null, "gcTimeout": 172800, "errorMessage": "Exit code: 1. Reason: Traceback (most recent call last):\n  File \"/home/user/app/app.py\", line 2, in <module>\n    import torch\nModuleNotFoundError: No module named 'torch'\n", "replicas": {"requested": 1}, "devMode": false, "domains": [{"domain": "consteve77-gpt-analysis2.hf.space", "stage": "READY"}]}, "shortDescription": "It predicts the next word in a sentence", "title": "Gpt Analysis2", "isLikedByUser": false, "trendingScore": 0}, {"author": "ArouldShock", "authorData": {"_id": "683443d4a7643618d8d0c286", "avatarUrl": "https://cdn-avatars.huggingface.co/v1/production/uploads/noauth/R3kHgKasNCzc2Iq0mILjt.jpeg", "fullname": "xdk", "name": "ArouldShock", "type": "user", "isPro": false, "isHf": false, "isHfAdmin": false, "isMod": false}, "colorFrom": "indigo", "colorTo": "red", "createdAt": "2025-05-31T02:15:30.000Z", "emoji": "♾️", "id": "ArouldShock/1", "lastModified": "2025-05-19T00:46:38.000Z", "likes": 0, "pinned": false, "private": false, "sdk": "gradio", "repoType": "space", "runtime": {"stage": "RUNNING", "hardware": {"current": "cpu-basic", "requested": "cpu-basic"}, "storage": null, "gcTimeout": 172800, "errorMessage": null, "replicas": {"current": 1, "requested": 1}, "devMode": false, "domains": [{"domain": "arouldshock-1.hf.space", "stage": "READY"}], "sha": "0ea029e380b7b46dac93106afdc079dccbbbcc34"}, "title": "Prompt Generator", "isLikedByUser": false, "originSpace": {"name": "ekuser/prompt-generator", "author": {"_id": "67c7b31210a301070d970941", "avatarUrl": "/avatars/94866a03447c1ac8e4d9fc4a70cdd7cc.svg", "fullname": "EK", "name": "ekuser", "type": "user", "isPro": false, "isHf": false, "isHfAdmin": false, "isMod": false, "followerCount": 1}}, "trendingScore": 0}, {"author": "gautammaheshwary27", "authorData": {"_id": "67b334194cb4b9706086cd24", "avatarUrl": "/avatars/4b5b24c97e79e0ff9e3c055e22ce3c91.svg", "fullname": "Gautam Maheshwary", "name": "gautammaheshwary27", "type": "user", "isPro": false, "isHf": false, "isHfAdmin": false, "isMod": false}, "colorFrom": "red", "colorTo": "red", "createdAt": "2025-05-31T02:12:20.000Z", "emoji": "🚀", "id": "gautammaheshwary27/Etymology_Study_of_Words", "lastModified": "2025-05-31T02:16:34.000Z", "likes": 0, "pinned": false, "private": false, "sdk": "docker", "repoType": "space", "runtime": {"stage": "RUNNING", "hardware": {"current": "cpu-basic", "requested": "cpu-basic"}, "storage": null, "gcTimeout": 172800, "replicas": {"current": 1, "requested": 1}, "devMode": false, "domains": [{"domain": "gautammaheshwary27-etymology-study-of-words.hf.space", "stage": "READY"}], "sha": "2f22fc6ab117024afbe6e04d881d011f1dc22d7e"}, "shortDescription": "Streamlit template space", "title": "Etymology Study Of Words", "isLikedByUser": false, "trendingScore": 0}, {"author": "TomHanJC", "authorData": {"_id": "67bca714f242bb3877745c3e", "avatarUrl": "https://cdn-avatars.huggingface.co/v1/production/uploads/no-auth/wceB35Tb7WIk5Wiq9BpWI.png", "fullname": "Tom", "name": "TomHanJC", "type": "user", "isPro": false, "isHf": false, "isHfAdmin": false, "isMod": false}, "colorFrom": "green", "colorTo": "purple", "createdAt": "2025-05-31T02:11:08.000Z", "emoji": "🏢", "id": "TomHanJC/tom", "lastModified": "2025-05-31T02:11:57.000Z", "likes": 0, "pinned": false, "private": false, "sdk": "docker", "repoType": "space", "runtime": {"stage": "RUNNING", "hardware": {"current": "cpu-basic", "requested": "cpu-basic"}, "storage": null, "gcTimeout": 172800, "errorMessage": null, "replicas": {"current": 1, "requested": 1}, "devMode": false, "domains": [{"domain": "tomhanjc-tom.hf.space", "stage": "READY"}], "sha": "4c6e315f42f5fb5e8d3a7136a35ea4345e87771c"}, "title": "Tom", "isLikedByUser": false, "trendingScore": 0}], "numItemsPerPage": 24, "numTotalItems": 496549, "pageIndex": 0}