{"spaces": [{"author": "Sun139Vn", "authorData": {"_id": "680afd82bbebf87944b04b8e", "avatarUrl": "/avatars/0c3dc4922ddbfc23e023e08a56195646.svg", "fullname": "Hai AN", "name": "Sun139Vn", "type": "user", "isPro": false, "isHf": false, "isHfAdmin": false, "isMod": false, "isUserFollowing": false}, "colorFrom": "gray", "colorTo": "purple", "createdAt": "2026-02-02T03:43:28.000Z", "emoji": "🐳", "id": "Sun139Vn/chemsafe-pro-factory", "lastModified": "2026-02-02T03:43:30.000Z", "likes": 0, "pinned": false, "private": false, "sdk": "static", "repoType": "space", "runtime": {"stage": "RUNNING", "hardware": {"current": null, "requested": null}, "storage": null, "replicas": {"requested": 1, "current": 1}}, "title": "ChemSafe Pro Factory 🧪", "isLikedByUser": false, "trendingScore": 0, "tags": ["static", "deepsite-v3", "region:us"], "featured": false}, {"author": "HiLight-AI", "authorData": {"_id": "67b296502a4cd1863924261b", "avatarUrl": "https://cdn-avatars.huggingface.co/v1/production/uploads/67b2949b55810ecdb3db8685/4mPUvHSnDc3OpJ4ctSfsn.png", "fullname": "HiLight Techonlogy Co.,Ltd.", "name": "HiLight-AI", "type": "org", "isHf": false, "isHfAdmin": false, "isMod": false, "plan": "team", "followerCount": 1, "isUserFollowing": false}, "colorFrom": "purple", "colorTo": "gray", "createdAt": "2026-02-02T03:43:10.000Z", "emoji": "🎮", "id": "HiLight-AI/waypoint-1-small", "lastModified": "2026-01-23T11:09:13.000Z", "likes": 0, "pinned": false, "private": false, "sdk": "gradio", "repoType": "space", "runtime": {"stage": "RUNTIME_ERROR", "hardware": {"current": null, "requested": "zero-a10g"}, "storage": null, "gcTimeout": 172800, "errorMessage": "Exit code: 1. Reason: ZeroGPU environment detected\nModular Diffusers is currently an experimental feature under active development. The API is subject to breaking changes in future releases.\nCompilation cache directory: /home/user/.cache/world_engine_compile\n`blocks` is `None`, no default blocks class found for ModularPipeline\nTraceback (most recent call last):\n  File \"/home/user/app/app.py\", line 58, in <module>\n    pipe = ModularPipeline.from_pretrained(MODEL_ID, trust_remote_code=True, revision=\"aot-compatible\")\n           ^^^^^^^^^^^^^^^^^^^^^^^^^^^^^^^^^^^^^^^^^^^^^^^^^^^^^^^^^^^^^^^^^^^^^^^^^^^^^^^^^^^^^^^^^^^^\n  File \"/usr/local/lib/python3.12/site-packages/huggingface_hub/utils/_validators.py\", line 114, in _inner_fn\n    return fn(*args, **kwargs)\n           ^^^^^^^^^^^^^^^^^^^\n  File \"/usr/local/lib/python3.12/site-packages/diffusers/modular_pipelines/modular_pipeline.py\", line 1705, in from_pretrained\n    pipeline = pipeline_class(\n               ^^^^^^^^^^^^^^^\n  File \"/usr/local/lib/python3.12/site-packages/diffusers/modular_pipelines/modular_pipeline.py\", line 1540, in __init__\n    self._component_specs = {spec.name: deepcopy(spec) for spec in self.blocks.expected_components}\n                                                                   ^^^^^^^^^^^^^^^^^^^^^^^^^^^^^^^\nAttributeError: 'NoneType' object has no attribute 'expected_components'\n", "replicas": {"requested": 1}, "devMode": false, "domains": [{"domain": "hilight-ai-waypoint-1-small.hf.space", "stage": "READY"}]}, "title": "Waypoint 1 Small", "isLikedByUser": false, "originRepo": {"name": "Overworld/waypoint-1-small", "author": {"_id": "694b209c141ed80221fcdb41", "avatarUrl": "https://cdn-avatars.huggingface.co/v1/production/uploads/60d35a0307da9c17c7270909/ZNdRiSES_ycJsV4FG3AdS.jpeg", "fullname": "Overworld", "name": "Overworld", "type": "org", "isHf": false, "isHfAdmin": false, "isMod": false, "plan": "team", "followerCount": 78, "isUserFollowing": false}}, "trendingScore": 0, "tags": ["gradio", "region:us"], "featured": false}, {"author": "tvdeidad", "authorData": {"_id": "69801afdc87d37dbd6b766e9", "avatarUrl": "/avatars/efc54a46b9ab0a4fe14f151bcd3834e3.svg", "fullname": "Widevine Deidad", "name": "tvdeidad", "type": "user", "isPro": false, "isHf": false, "isHfAdmin": false, "isMod": false, "isUserFollowing": false}, "colorFrom": "indigo", "colorTo": "green", "createdAt": "2026-02-02T03:39:46.000Z", "emoji": "🏆", "id": "tvdeidad/f", "lastModified": "2026-02-02T03:40:27.000Z", "likes": 0, "pinned": false, "private": false, "sdk": "docker", "repoType": "space", "runtime": {"stage": "RUNNING", "hardware": {"current": "cpu-basic", "requested": "cpu-basic"}, "storage": null, "gcTimeout": 172800, "replicas": {"current": 1, "requested": 1}, "devMode": false, "domains": [{"domain": "tvdeidad-f.hf.space", "stage": "READY"}], "sha": "998c7a644b562c6924d7dc9bb4c250589818595d"}, "shortDescription": "La letra f :trol3d:", "title": "F", "isLikedByUser": false, "trendingScore": 0, "tags": ["docker", "region:us"], "featured": false}, {"author": "jana21", "authorData": {"_id": "67723b77b3163a95a661ccd6", "avatarUrl": "/avatars/9d10ead7c102c0a0edf5be319d3975b3.svg", "fullname": "Jannatun Naim", "name": "jana21", "type": "user", "isPro": false, "isHf": false, "isHfAdmin": false, "isMod": false, "isUserFollowing": false}, "colorFrom": "gray", "colorTo": "gray", "createdAt": "2026-02-02T03:39:24.000Z", "emoji": "🚀", "id": "jana21/trackio", "lastModified": "2026-02-02T03:39:25.000Z", "likes": 0, "pinned": false, "private": false, "sdk": "gradio", "repoType": "space", "runtime": {"stage": "RUNNING", "hardware": {"current": "cpu-basic", "requested": "cpu-basic"}, "storage": null, "gcTimeout": 172800, "replicas": {"current": 1, "requested": 1}, "devMode": false, "domains": [{"domain": "jana21-trackio.hf.space", "stage": "READY"}], "sha": "aa2defae8f92ec4fad5f41db9a683fe2e7598e5c"}, "title": "Trackio", "isLikedByUser": false, "trendingScore": 0, "tags": ["gradio", "trackio", "region:us"], "featured": false}, {"author": "aisvarya-adeseye", "authorData": {"_id": "67d207d6bd98479531cbf65f", "avatarUrl": "/avatars/be3b9ca10ca62ecba066ad87433066da.svg", "fullname": "Aisvarya Adeseye", "name": "aisvarya-adeseye", "type": "user", "isPro": false, "isHf": false, "isHfAdmin": false, "isMod": false, "isUserFollowing": false}, "colorFrom": "yellow", "colorTo": "purple", "createdAt": "2026-02-02T03:38:30.000Z", "emoji": "💬", "id": "aisvarya-adeseye/TestSpace", "lastModified": "2026-02-02T03:38:31.000Z", "likes": 0, "pinned": false, "private": false, "sdk": "gradio", "repoType": "space", "runtime": {"stage": "RUNNING", "hardware": {"current": "cpu-basic", "requested": "cpu-basic"}, "storage": null, "gcTimeout": 172800, "replicas": {"current": 1, "requested": 1}, "devMode": false, "domains": [{"domain": "aisvarya-adeseye-testspace.hf.space", "stage": "READY"}], "sha": "d59558146ad7c7735788f2f9c52d4120378e1fc8"}, "title": "TestSpace", "isLikedByUser": false, "trendingScore": 0, "tags": ["gradio", "region:us"], "featured": false}, {"author": "Prano2", "authorData": {"_id": "69124473298751d8732149a1", "avatarUrl": "/avatars/d85fa016a607573c260e3fbff1441df1.svg", "fullname": "Pranotosh Mandal", "name": "Prano2", "type": "user", "isPro": false, "isHf": false, "isHfAdmin": false, "isMod": false, "isUserFollowing": false}, "colorFrom": "red", "colorTo": "red", "createdAt": "2026-02-02T03:38:01.000Z", "emoji": "🚀", "id": "Prano2/voice-assistant", "lastModified": "2026-02-02T03:42:09.000Z", "likes": 0, "pinned": false, "private": false, "sdk": "docker", "repoType": "space", "runtime": {"stage": "RUNNING", "hardware": {"current": "cpu-basic", "requested": "cpu-basic"}, "storage": null, "gcTimeout": 172800, "replicas": {"current": 1, "requested": 1}, "devMode": false, "domains": [{"domain": "prano2-voice-assistant.hf.space", "stage": "READY"}], "sha": "f09db8274d245248cf4fe50ddd05092b6c4492e1"}, "shortDescription": "Streamlit template space", "title": "Voice Assistant", "isLikedByUser": false, "trendingScore": 0, "tags": ["docker", "streamlit", "region:us"], "featured": false}, {"author": "Erfan-Shayegani", "authorData": {"_id": "64a0784d7b57fab3a5d63868", "avatarUrl": "https://cdn-avatars.huggingface.co/v1/production/uploads/64a0784d7b57fab3a5d63868/iqA0qF0nYAstSWsSS94RH.png", "fullname": "Erfan Shayegani 😈", "name": "Erfan-Shayegani", "type": "user", "isPro": false, "isHf": false, "isHfAdmin": false, "isMod": false, "followerCount": 7, "isUserFollowing": false}, "colorFrom": "gray", "colorTo": "gray", "createdAt": "2026-02-02T03:38:00.000Z", "emoji": "🚀", "id": "Erfan-Shayegani/trackio", "lastModified": "2026-02-02T03:38:02.000Z", "likes": 0, "pinned": false, "private": false, "sdk": "gradio", "repoType": "space", "runtime": {"stage": "RUNNING", "hardware": {"current": "cpu-basic", "requested": "cpu-basic"}, "storage": null, "gcTimeout": 172800, "replicas": {"current": 1, "requested": 1}, "devMode": false, "domains": [{"domain": "erfan-shayegani-trackio.hf.space", "stage": "READY"}], "sha": "d4e40fddcc71a780eec889babf4f544b18f4e06a"}, "title": "Trackio", "isLikedByUser": false, "trendingScore": 0, "tags": ["gradio", "trackio", "region:us"], "featured": false}, {"author": "asmrhi", "authorData": {"_id": "6977bccbbe4db8cc2553dbd0", "avatarUrl": "/avatars/cc9b68d296c7419a074803ae3d8196bd.svg", "fullname": "Rimsha Mahmood", "name": "asmrhi", "type": "user", "isPro": false, "isHf": false, "isHfAdmin": false, "isMod": false, "isUserFollowing": false}, "colorFrom": "red", "colorTo": "red", "createdAt": "2026-02-02T03:37:51.000Z", "emoji": "🚀", "id": "asmrhi/mediguard-assistant", "lastModified": "2026-02-02T03:37:52.000Z", "likes": 0, "pinned": false, "private": false, "sdk": "docker", "repoType": "space", "runtime": {"stage": "RUNNING", "hardware": {"current": "cpu-basic", "requested": "cpu-basic"}, "storage": null, "gcTimeout": 172800, "replicas": {"current": 1, "requested": 1}, "devMode": false, "domains": [{"domain": "asmrhi-mediguard-assistant.hf.space", "stage": "READY"}], "sha": "51c88a4dd0c577c2ab698304056ee40e5a2f1b32"}, "shortDescription": "Streamlit template space", "title": "Mediguard Assistant", "isLikedByUser": false, "trendingScore": 0, "tags": ["docker", "streamlit", "region:us"], "featured": false}, {"author": "Cardsmen2017", "authorData": {"_id": "69801aff0ec9f243713564c4", "avatarUrl": "/avatars/01011b333c17cc20311282a18210b586.svg", "fullname": "Diego Esquivel Valtierra", "name": "Cardsmen2017", "type": "user", "isPro": false, "isHf": false, "isHfAdmin": false, "isMod": false, "isUserFollowing": false}, "colorFrom": "green", "colorTo": "green", "createdAt": "2026-02-02T03:36:01.000Z", "emoji": "👀", "id": "Cardsmen2017/RVC_HFv2", "lastModified": "2026-01-11T03:43:42.000Z", "likes": 0, "pinned": false, "private": false, "sdk": "gradio", "repoType": "space", "runtime": {"stage": "BUILD_ERROR", "hardware": {"current": null, "requested": "cpu-basic"}, "storage": null, "gcTimeout": 172800, "errorMessage": "Job failed with exit code: 1. Reason: cache miss: [base 9/9] RUN mkdir -p /home/user && ( [ -e /home/user/app ] || ln -s /app/ /home/user/app ) || true\ncache miss: [base 6/9] RUN --mount=target=/tmp/pre-requirements.txt,source=pre-requirements.txt     pip install --no-cache-dir -r /tmp/pre-requirements.txt\ncache miss: [run 1/2] COPY --link ./ /app\ncache miss: [base 8/9] RUN pip install --no-cache-dir     gradio[oauth]==3.43.2     \"uvicorn>=0.14.0\" \"websockets>=10.4\"     spaces\ncache miss: [run 1/2] LINK COPY --link ./ /app\ncache miss: [run 2/2] LINK COPY --from=pipfreeze --link /pipfreeze/ /pipfreeze/\ncache miss: [pipfreeze 2/2] RUN pip freeze > /pipfreeze/freeze.txt\ncache miss: [base 7/9] RUN --mount=target=/tmp/requirements.txt,source=requirements.txt     pip install --no-cache-dir -r /tmp/requirements.txt\ncache miss: [pipfreeze 1/2] RUN mkdir -p /pipfreeze\ncache miss: [base 5/9] RUN --mount=target=/tmp/packages.txt,source=packages.txt \tapt-get update && \txargs -r -a /tmp/packages.txt apt-get install -y && \trm -rf /var/lib/apt/lists/*\ncache miss: [run 2/2] COPY --from=pipfreeze --link /pipfreeze/ /pipfreeze/\n{\"total\":27,\"completed\":20,\"user_total\":16,\"user_cached\":4,\"user_completed\":9,\"user_cacheable\":15,\"from\":1,\"miss\":11,\"client_duration_ms\":25646}\n", "replicas": {"requested": 1}, "devMode": false, "domains": [{"domain": "cardsmen2017-rvc-hfv2.hf.space", "stage": "READY"}]}, "title": "RVC Inference HF", "isLikedByUser": false, "originRepo": {"name": "r3gm/RVC_HFv2", "author": {"_id": "63e6e242b6a40bf941e520d5", "avatarUrl": "https://cdn-avatars.huggingface.co/v1/production/uploads/63e6e242b6a40bf941e520d5/-T6LxA2WbWpgXZKGWqr9T.jpeg", "fullname": "Roger Condori", "name": "r3gm", "type": "user", "isPro": false, "isHf": false, "isHfAdmin": false, "isMod": false, "followerCount": 428, "isUserFollowing": false}}, "trendingScore": 0, "tags": ["gradio", "region:us"], "featured": false}, {"author": "swiiwii", "authorData": {"_id": "64282b126268f155b77aa02a", "avatarUrl": "/avatars/1a837b010066ae1f611a8a36dea41ba6.svg", "fullname": "swiiwii", "name": "swiiwii", "type": "user", "isPro": false, "isHf": false, "isHfAdmin": false, "isMod": false, "isUserFollowing": false}, "colorFrom": "gray", "colorTo": "gray", "createdAt": "2026-02-02T03:34:05.000Z", "emoji": "🚀", "id": "swiiwii/career_conversation", "lastModified": "2026-02-02T03:34:06.000Z", "likes": 0, "pinned": false, "private": false, "sdk": "gradio", "repoType": "space", "runtime": {"stage": "RUNNING", "hardware": {"current": "cpu-basic", "requested": "cpu-basic"}, "storage": null, "gcTimeout": 172800, "replicas": {"current": 1, "requested": 1}, "devMode": false, "domains": [{"domain": "swiiwii-career-conversation.hf.space", "stage": "READY"}], "sha": "799da702147737d655ca8db26a4e50a55b23d96d"}, "title": "career_conversation", "isLikedByUser": false, "trendingScore": 0, "tags": ["gradio", "region:us"], "featured": false}, {"author": "ibragimislam", "authorData": {"_id": "698019bebc657313c1fa49d1", "avatarUrl": "/avatars/0bae588d8f59b9b4ed7c642925221f75.svg", "fullname": "islam", "name": "ibragimislam", "type": "user", "isPro": false, "isHf": false, "isHfAdmin": false, "isMod": false, "isUserFollowing": false}, "colorFrom": "blue", "colorTo": "yellow", "createdAt": "2026-02-02T03:33:30.000Z", "emoji": "👁", "id": "ibragimislam/Wan2.2-Animate", "lastModified": "2026-01-23T07:17:48.000Z", "likes": 0, "pinned": false, "private": false, "sdk": "gradio", "repoType": "space", "runtime": {"stage": "RUNNING", "hardware": {"current": "cpu-basic", "requested": "cpu-basic"}, "storage": null, "gcTimeout": 172800, "replicas": {"current": 1, "requested": 1}, "devMode": false, "domains": [{"domain": "ibragimislam-wan2-2-animate.hf.space", "stage": "READY"}], "sha": "708bb0f7bb6e383d973d6f12888af685dff5be00"}, "shortDescription": "Wan2.2 Animate", "title": "Wan2.2 Animate", "isLikedByUser": false, "originRepo": {"name": "Wan-AI/Wan2.2-Animate", "author": {"_id": "67bc7cd418dd753c02a82684", "avatarUrl": "https://cdn-avatars.huggingface.co/v1/production/uploads/67b610677ea7952def8b29c6/N6jQbbeaa_FcUY-wI1dgG.png", "fullname": "Wan-AI", "name": "Wan-AI", "type": "org", "isHf": false, "isHfAdmin": false, "isMod": false, "followerCount": 7920, "isUserFollowing": false}}, "trendingScore": 0, "tags": ["gradio", "region:us"], "featured": false}, {"author": "NVRD13", "authorData": {"_id": "6980195ae00765f29c521e52", "avatarUrl": "/avatars/23b3f5ebf47a91bb5589a4d2b8b78bd3.svg", "fullname": "NVRD13", "name": "NVRD13", "type": "user", "isPro": false, "isHf": false, "isHfAdmin": false, "isMod": false, "isUserFollowing": false}, "colorFrom": "gray", "colorTo": "gray", "createdAt": "2026-02-02T03:33:18.000Z", "emoji": "🐢", "id": "NVRD13/dark-symphony-metal-maestro-s-realm", "lastModified": "2026-02-02T03:33:18.000Z", "likes": 0, "pinned": false, "private": false, "sdk": "static", "repoType": "space", "runtime": {"stage": "RUNNING", "hardware": {"current": null, "requested": null}, "storage": null, "replicas": {"requested": 1, "current": 1}}, "title": "Dark Symphony Metal Maestro S Realm", "isLikedByUser": false, "trendingScore": 0, "tags": ["static", "region:us"], "featured": false}, {"author": "TheUniversalCreator", "authorData": {"_id": "69801659d57c056d9b63a457", "avatarUrl": "/avatars/83ae594d97f4f64d8b0eed5a50ff570e.svg", "fullname": "The Creator", "name": "TheUniversalCreator", "type": "user", "isPro": false, "isHf": false, "isHfAdmin": false, "isMod": false, "isUserFollowing": false}, "colorFrom": "yellow", "colorTo": "red", "createdAt": "2026-02-02T03:28:43.000Z", "emoji": "🐳", "id": "TheUniversalCreator/fuchsiagold-money-maker", "lastModified": "2026-02-02T03:28:43.000Z", "likes": 0, "pinned": false, "private": false, "sdk": "static", "repoType": "space", "runtime": {"stage": "RUNNING", "hardware": {"current": null, "requested": null}, "storage": null, "replicas": {"requested": 1, "current": 1}}, "title": "FuchsiaGold Money Maker 🚀", "isLikedByUser": false, "trendingScore": 0, "tags": ["static", "deepsite-v3", "region:us"], "featured": false}, {"author": "mlfonso18", "authorData": {"_id": "697ff65c01d0d68355cbda7c", "avatarUrl": "https://cdn-avatars.huggingface.co/v1/production/uploads/no-auth/LkZ_-QalJkQj2FuVQyhk8.png", "fullname": "Manuel Alfonso", "name": "mlfonso18", "type": "user", "isPro": false, "isHf": false, "isHfAdmin": false, "isMod": false, "isUserFollowing": false}, "colorFrom": "blue", "colorTo": "green", "createdAt": "2026-02-02T03:26:47.000Z", "emoji": "📊", "id": "mlfonso18/Prompt_Final", "lastModified": "2026-02-02T03:42:27.000Z", "likes": 0, "pinned": false, "private": false, "sdk": "gradio", "repoType": "space", "runtime": {"stage": "RUNTIME_ERROR", "hardware": {"current": null, "requested": "cpu-basic"}, "storage": null, "gcTimeout": 172800, "errorMessage": "Exit code: 0. Reason: ", "replicas": {"requested": 1}, "devMode": false, "domains": [{"domain": "mlfonso18-prompt-final.hf.space", "stage": "READY"}]}, "shortDescription": "Construye  Contenidos  con Mistral", "title": "Prompt Final", "isLikedByUser": false, "trendingScore": 0, "tags": ["gradio", "region:us"], "featured": false}, {"author": "jallebw2", "authorData": {"_id": "68605f3026b733675122049f", "avatarUrl": "/avatars/9584a93d4ac59afc7f402630b1d23ea1.svg", "fullname": "Wael Jalleb", "name": "jallebw2", "type": "user", "isPro": false, "isHf": false, "isHfAdmin": false, "isMod": false, "isUserFollowing": false}, "colorFrom": "indigo", "colorTo": "indigo", "createdAt": "2026-02-02T03:26:34.000Z", "emoji": "🏢", "id": "jallebw2/anycoder", "lastModified": "2025-09-25T06:40:10.000Z", "likes": 0, "pinned": false, "private": false, "sdk": "gradio", "repoType": "space", "runtime": {"stage": "RUNTIME_ERROR", "hardware": {"current": null, "requested": "cpu-basic"}, "storage": null, "gcTimeout": 172800, "errorMessage": "Exit code: 1. Reason: Traceback (most recent call last):\n  File \"/app/app.py\", line 2011, in <module>\n    raise RuntimeError(\"HF_TOKEN environment variable is not set. Please set it to your Hugging Face API token.\")\nRuntimeError: HF_TOKEN environment variable is not set. Please set it to your Hugging Face API token.\n", "replicas": {"requested": 1}, "devMode": false, "domains": [{"domain": "jallebw2-anycoder.hf.space", "stage": "READY"}]}, "title": "Anycoder", "isLikedByUser": false, "originRepo": {"name": "cafe3310/anycoder", "author": {"_id": "678143d4ddb1f1ce16daca8e", "avatarUrl": "https://cdn-avatars.huggingface.co/v1/production/uploads/678143d4ddb1f1ce16daca8e/qg8Y6-ydHgELl1Gn95das.png", "fullname": "cafe3310", "name": "cafe3310", "type": "user", "isPro": true, "isHf": false, "isHfAdmin": false, "isMod": false, "followerCount": 18, "isUserFollowing": false}}, "trendingScore": 0, "tags": ["gradio", "region:us"], "featured": false}, {"author": "NamuTechnology", "authorData": {"_id": "67a04102d9b5bce3e4e35bb6", "avatarUrl": "https://cdn-avatars.huggingface.co/v1/production/uploads/67a04102d9b5bce3e4e35bb6/PEKQfGxPMN47ORCCRKosJ.png", "fullname": "NamuTechnology", "name": "NamuTechnology", "type": "user", "isPro": false, "isHf": false, "isHfAdmin": false, "isMod": false, "followerCount": 1, "isUserFollowing": false}, "colorFrom": "yellow", "colorTo": "purple", "createdAt": "2026-02-02T03:26:19.000Z", "emoji": "💬", "id": "NamuTechnology/NamuLM", "lastModified": "2026-02-02T03:39:33.000Z", "likes": 0, "pinned": false, "private": false, "sdk": "gradio", "repoType": "space", "runtime": {"stage": "RUNTIME_ERROR", "hardware": {"current": null, "requested": "cpu-basic"}, "storage": null, "gcTimeout": 172800, "errorMessage": "Exit code: 1. Reason: Traceback (most recent call last):\n  File \"/app/app.py\", line 2, in <module>\n    from transformers import AutoModelForCausalLM, AutoTokenizer\n  File \"/usr/local/lib/python3.13/site-packages/transformers/__init__.py\", line 30, in <module>\n    from . import dependency_versions_check\n  File \"/usr/local/lib/python3.13/site-packages/transformers/dependency_versions_check.py\", line 16, in <module>\n    from .utils.versions import require_version, require_version_core\n  File \"/usr/local/lib/python3.13/site-packages/transformers/utils/__init__.py\", line 77, in <module>\n    from .hub import (\n    ...<19 lines>...\n    )\n  File \"/usr/local/lib/python3.13/site-packages/transformers/utils/hub.py\", line 29, in <module>\n    from huggingface_hub import (\n    ...<14 lines>...\n    )\nImportError: cannot import name 'is_offline_mode' from 'huggingface_hub' (/usr/local/lib/python3.13/site-packages/huggingface_hub/__init__.py)\n", "replicas": {"requested": 1}, "devMode": false, "domains": [{"domain": "namutechnology-namulm.hf.space", "stage": "READY"}]}, "shortDescription": "NamuLM", "title": "NamuLM", "isLikedByUser": false, "trendingScore": 0, "tags": ["gradio", "region:us"], "featured": false}, {"author": "daldorim", "authorData": {"_id": "69800ba7d742adcb7e788a71", "avatarUrl": "/avatars/d66bc24b22d8b7b75394ef3def587a4b.svg", "fullname": "Do", "name": "daldorim", "type": "user", "isPro": false, "isHf": false, "isHfAdmin": false, "isMod": false, "isUserFollowing": false}, "colorFrom": "red", "colorTo": "pink", "createdAt": "2026-02-02T03:26:12.000Z", "emoji": "👁", "id": "daldorim/Flower", "lastModified": "2026-02-02T03:44:00.000Z", "likes": 0, "pinned": false, "private": false, "sdk": "gradio", "repoType": "space", "runtime": {"stage": "APP_STARTING", "hardware": {"current": null, "requested": "cpu-basic"}, "storage": null, "gcTimeout": 172800, "errorMessage": null, "replicas": {"requested": 1}, "devMode": false, "domains": [{"domain": "daldorim-flower.hf.space", "stage": "READY"}]}, "shortDescription": "Object", "title": "Flower", "isLikedByUser": false, "trendingScore": 0, "tags": ["gradio", "region:us"], "featured": false}, {"author": "pkumarsatish", "authorData": {"_id": "656ab961e8bf55919a45dd8e", "avatarUrl": "/avatars/4c6e323f5a2410d3cca410626e521667.svg", "fullname": "Satish Kumar", "name": "pkumarsatish", "type": "user", "isPro": false, "isHf": false, "isHfAdmin": false, "isMod": false, "isUserFollowing": false}, "colorFrom": "pink", "colorTo": "yellow", "createdAt": "2026-02-02T03:25:49.000Z", "emoji": "⚡", "id": "pkumarsatish/First_agent_template", "lastModified": "2025-05-06T08:19:21.000Z", "likes": 0, "pinned": false, "private": false, "sdk": "gradio", "repoType": "space", "runtime": {"stage": "RUNNING", "hardware": {"current": "cpu-basic", "requested": "cpu-basic"}, "storage": null, "gcTimeout": 172800, "replicas": {"current": 1, "requested": 1}, "devMode": false, "domains": [{"domain": "pkumarsatish-first-agent-template.hf.space", "stage": "READY"}], "sha": "8c5c24b6f1ed08e7fd34a59f44e854580def9101"}, "title": "First Agent Template", "isLikedByUser": false, "originRepo": {"name": "agents-course/First_agent_template", "author": {"_id": "67879bb5e6e3eea9ff32fbd8", "avatarUrl": "https://cdn-avatars.huggingface.co/v1/production/uploads/60cae820b1c79a3e4b436664/gSOeYxuhnE0U0HFeh__wA.png", "fullname": "Hugging Face Agents Course", "name": "agents-course", "type": "org", "isHf": false, "isHfAdmin": false, "isMod": false, "plan": "team", "followerCount": 53791, "isUserFollowing": false}}, "trendingScore": 0, "tags": ["gradio", "smolagents", "agent", "smolagent", "tool", "agent-course", "region:us"], "featured": false}, {"author": "jallebw2", "authorData": {"_id": "68605f3026b733675122049f", "avatarUrl": "/avatars/9584a93d4ac59afc7f402630b1d23ea1.svg", "fullname": "Wael Jalleb", "name": "jallebw2", "type": "user", "isPro": false, "isHf": false, "isHfAdmin": false, "isMod": false, "isUserFollowing": false}, "colorFrom": "yellow", "colorTo": "blue", "createdAt": "2026-02-02T03:23:06.000Z", "emoji": "🌍", "id": "jallebw2/CogVideoX-Fun-5b-custom", "lastModified": "2024-09-30T06:15:21.000Z", "likes": 0, "pinned": false, "private": false, "sdk": "gradio", "repoType": "space", "runtime": {"stage": "RUNTIME_ERROR", "hardware": {"current": null, "requested": "cpu-basic"}, "storage": null, "gcTimeout": 172800, "errorMessage": "Exit code: 1. Reason: in <module>\n    import gradio as gr\n  File \"/usr/local/lib/python3.13/site-packages/gradio/__init__.py\", line 3, in <module>\n    import gradio._simple_templates\n  File \"/usr/local/lib/python3.13/site-packages/gradio/_simple_templates/__init__.py\", line 1, in <module>\n    from .simpledropdown import SimpleDropdown\n  File \"/usr/local/lib/python3.13/site-packages/gradio/_simple_templates/simpledropdown.py\", line 6, in <module>\n    from gradio.components.base import Component, FormComponent\n  File \"/usr/local/lib/python3.13/site-packages/gradio/components/__init__.py\", line 1, in <module>\n    from gradio.components.annotated_image import AnnotatedImage\n  File \"/usr/local/lib/python3.13/site-packages/gradio/components/annotated_image.py\", line 14, in <module>\n    from gradio.components.base import Component\n  File \"/usr/local/lib/python3.13/site-packages/gradio/components/base.py\", line 20, in <module>\n    from gradio.blocks import Block, BlockContext\n  File \"/usr/local/lib/python3.13/site-packages/gradio/blocks.py\", line 39, in <module>\n    from gradio import (\n    ...<10 lines>...\n    )\n  File \"/usr/local/lib/python3.13/site-packages/gradio/networking.py\", line 15, in <module>\n    from gradio.routes import App  # HACK: to avoid circular import # noqa: F401\n    ^^^^^^^^^^^^^^^^^^^^^^^^^^^^^\n  File \"/usr/local/lib/python3.13/site-packages/gradio/routes.py\", line 69, in <module>\n    from gradio import ranged_response, route_utils, utils, wasm_utils\n  File \"/usr/local/lib/python3.13/site-packages/gradio/route_utils.py\", line 53, in <module>\n    from gradio.helpers import EventData\n  File \"/usr/local/lib/python3.13/site-packages/gradio/helpers.py\", line 26, in <module>\n    from gradio import components, oauth, processing_utils, routes, utils, wasm_utils\n  File \"/usr/local/lib/python3.13/site-packages/gradio/oauth.py\", line 13, in <module>\n    from huggingface_hub import HfFolder, whoami\nImportError: cannot import name 'HfFolder' from 'huggingface_hub' (/usr/local/lib/python3.13/site-packages/huggingface_hub/__init__.py)\n", "replicas": {"requested": 1}, "devMode": false, "domains": [{"domain": "jallebw2-cogvideox-fun-5b-custom.hf.space", "stage": "READY"}]}, "title": "CogVideoX Fun 5b", "isLikedByUser": false, "originRepo": {"name": "K00B404/CogVideoX-Fun-5b-custom", "author": {"_id": "64aa878281dda4817269395d", "avatarUrl": "https://cdn-avatars.huggingface.co/v1/production/uploads/64aa878281dda4817269395d/OkeiTI-2SU0C86DXG3fNT.png", "fullname": "koo", "name": "K00B404", "type": "user", "isPro": false, "isHf": false, "isHfAdmin": false, "isMod": false, "followerCount": 15, "isUserFollowing": false}}, "trendingScore": 0, "tags": ["gradio", "region:us"], "featured": false}, {"author": "xi32", "authorData": {"_id": "698017ec68ae708338cf403e", "avatarUrl": "/avatars/0c94d4723aaac75f667746f97c502d8b.svg", "fullname": "Mo Chen", "name": "xi32", "type": "user", "isPro": false, "isHf": false, "isHfAdmin": false, "isMod": false, "isUserFollowing": false}, "colorFrom": "pink", "colorTo": "yellow", "createdAt": "2026-02-02T03:22:45.000Z", "emoji": "⚡", "id": "xi32/First_agent_template", "lastModified": "2025-05-06T08:19:21.000Z", "likes": 0, "pinned": false, "private": false, "sdk": "gradio", "repoType": "space", "runtime": {"stage": "RUNNING", "hardware": {"current": "cpu-basic", "requested": "cpu-basic"}, "storage": null, "gcTimeout": 172800, "replicas": {"current": 1, "requested": 1}, "devMode": false, "domains": [{"domain": "xi32-first-agent-template.hf.space", "stage": "READY"}], "sha": "8c5c24b6f1ed08e7fd34a59f44e854580def9101"}, "title": "First Agent Template", "isLikedByUser": false, "originRepo": {"name": "agents-course/First_agent_template", "author": {"_id": "67879bb5e6e3eea9ff32fbd8", "avatarUrl": "https://cdn-avatars.huggingface.co/v1/production/uploads/60cae820b1c79a3e4b436664/gSOeYxuhnE0U0HFeh__wA.png", "fullname": "Hugging Face Agents Course", "name": "agents-course", "type": "org", "isHf": false, "isHfAdmin": false, "isMod": false, "plan": "team", "followerCount": 53791, "isUserFollowing": false}}, "trendingScore": 0, "tags": ["gradio", "smolagents", "agent", "smolagent", "tool", "agent-course", "region:us"], "featured": false}, {"author": "kingkalau", "authorData": {"_id": "698016ccee7aa39f4e294f70", "avatarUrl": "/avatars/eafef14a1016b81892a397766c46cfa5.svg", "fullname": "kingka lau", "name": "kingkalau", "type": "user", "isPro": false, "isHf": false, "isHfAdmin": false, "isMod": false, "isUserFollowing": false}, "colorFrom": "yellow", "colorTo": "gray", "createdAt": "2026-02-02T03:21:57.000Z", "emoji": "🐨", "id": "kingkalau/kingkatv", "lastModified": "2026-02-02T03:39:53.000Z", "likes": 0, "pinned": false, "private": false, "sdk": "docker", "repoType": "space", "runtime": {"stage": "RUNNING", "hardware": {"current": "cpu-basic", "requested": "cpu-basic"}, "storage": null, "gcTimeout": 172800, "replicas": {"current": 1, "requested": 1}, "devMode": false, "domains": [{"domain": "kingkalau-kingkatv.hf.space", "stage": "READY"}], "sha": "0e8f2619b1dc9fbd4ddc5fced330058058ed5adf"}, "title": "Kingkatv", "isLikedByUser": false, "trendingScore": 0, "tags": ["docker", "region:us"], "featured": false}, {"author": "bt69", "authorData": {"_id": "67715e4bbb74df9800867285", "avatarUrl": "https://cdn-avatars.huggingface.co/v1/production/uploads/no-auth/L7LUblSKK4lG9b9gpig5v.png", "fullname": "Rahul Sharma", "name": "bt69", "type": "user", "isPro": false, "isHf": false, "isHfAdmin": false, "isMod": false, "isUserFollowing": false}, "colorFrom": "green", "colorTo": "pink", "createdAt": "2026-02-02T03:20:49.000Z", "emoji": "👁", "id": "bt69/TestZm3", "lastModified": "2026-02-02T03:21:19.000Z", "likes": 0, "pinned": false, "private": false, "sdk": "docker", "repoType": "space", "runtime": {"stage": "RUNTIME_ERROR", "hardware": {"current": null, "requested": "cpu-basic"}, "storage": null, "gcTimeout": 172800, "errorMessage": "Exit code: 1. Reason: o: https://github.com/rachelhasbigtits69/ZM3/\nINFO | From root -> update line no: 48 | Entered upstream branch: main\nINFO | From root -> update line no: 64 | Fetching latest updates...\nINFO | From root -> update line no: 66 | Successfully updated...\nINFO | From root -> update line no: 67 | Thanks For Using @Z_Mirror\n[2026-02-02 03:22:01 +0000] [37] [INFO] Starting gunicorn 21.2.0\n[2026-02-02 03:22:01 +0000] [37] [INFO] Listening at: http://0.0.0.0:80 (37)\n[2026-02-02 03:22:01 +0000] [37] [INFO] Using worker: gevent\n[2026-02-02 03:22:01 +0000] [61] [INFO] Booting worker with pid: 61\nTraceback (most recent call last):\n  File \"/usr/lib/python3.10/runpy.py\", line 187, in _run_module_as_main\n    mod_name, mod_spec, code = _get_module_details(mod_name, _Error)\n  File \"/usr/lib/python3.10/runpy.py\", line 146, in _get_module_details\n    return _get_module_details(pkg_main_name, error)\n  File \"/usr/lib/python3.10/runpy.py\", line 110, in _get_module_details\n    __import__(pkg_name)\n  File \"/usr/src/app/bot/__init__.py\", line 604, in <module>\n    ).start()\n  File \"/usr/local/lib/python3.10/dist-packages/pyrogram/sync.py\", line 66, in async_to_sync_wrap\n    return loop.run_until_complete(coroutine)\n  File \"uvloop/loop.pyx\", line 1517, in uvloop.loop.Loop.run_until_complete\n  File \"/usr/local/lib/python3.10/dist-packages/pyrogram/methods/utilities/start.py\", line 58, in start\n    is_authorized = await self.connect()\n  File \"/usr/local/lib/python3.10/dist-packages/pyrogram/methods/auth/connect.py\", line 40, in connect\n    await self.load_session()\n  File \"/usr/local/lib/python3.10/dist-packages/pyrogram/client.py\", line 620, in load_session\n    await Auth(\n  File \"/usr/local/lib/python3.10/dist-packages/pyrogram/session/auth.py\", line 255, in create\n    raise e\n  File \"/usr/local/lib/python3.10/dist-packages/pyrogram/session/auth.py\", line 85, in create\n    await self.connection.connect()\n  File \"/usr/local/lib/python3.10/dist-packages/pyrogram/connection/connection.py\", line 74, in connect\n    raise TimeoutError\nTimeoutError\n", "replicas": {"requested": 1}, "devMode": false, "domains": [{"domain": "bt69-testzm3.hf.space", "stage": "READY"}]}, "title": "TestZm3", "isLikedByUser": false, "trendingScore": 0, "tags": ["docker", "region:us"], "featured": false}, {"author": "ferhatkaraduman", "authorData": {"_id": "693dbba18da0a6a7f3493379", "avatarUrl": "/avatars/bf16065d9d2d970ba39a5df0bc7c3e48.svg", "fullname": "FERHAT KARADUMAN", "name": "ferhatkaraduman", "type": "user", "isPro": false, "isHf": false, "isHfAdmin": false, "isMod": false, "isUserFollowing": false}, "colorFrom": "pink", "colorTo": "green", "createdAt": "2026-02-02T03:19:50.000Z", "emoji": "🏆", "id": "ferhatkaraduman/TamirGPT", "lastModified": "2026-02-02T03:34:41.000Z", "likes": 0, "pinned": false, "private": false, "sdk": "gradio", "repoType": "space", "runtime": {"stage": "RUNNING", "hardware": {"current": "cpu-basic", "requested": "cpu-basic"}, "storage": null, "gcTimeout": 172800, "replicas": {"current": 1, "requested": 1}, "devMode": false, "domains": [{"domain": "ferhatkaraduman-tamirgpt.hf.space", "stage": "READY"}], "sha": "ac5a49a60c0049450c5b54251e03f232f0caf6c7"}, "shortDescription": "Tamir AI", "title": "TamirGPT", "isLikedByUser": false, "trendingScore": 0, "tags": ["gradio", "region:us"], "featured": false}, {"author": "meenu517", "authorData": {"_id": "697c775749815104ad65fcbd", "avatarUrl": "https://cdn-avatars.huggingface.co/v1/production/uploads/no-auth/3TNz2g9EibjflpLPtsmyA.png", "fullname": "Meenu G", "name": "meenu517", "type": "user", "isPro": false, "isHf": false, "isHfAdmin": false, "isMod": false, "isUserFollowing": false}, "colorFrom": "red", "colorTo": "red", "createdAt": "2026-02-02T03:14:53.000Z", "emoji": "🚀", "id": "meenu517/streamlit-frontend-churn", "lastModified": "2026-02-02T03:16:08.000Z", "likes": 0, "pinned": false, "private": false, "sdk": "docker", "repoType": "space", "runtime": {"stage": "RUNNING", "hardware": {"current": "cpu-basic", "requested": "cpu-basic"}, "storage": null, "gcTimeout": 172800, "replicas": {"current": 1, "requested": 1}, "devMode": false, "domains": [{"domain": "meenu517-streamlit-frontend-churn.hf.space", "stage": "READY"}], "sha": "7d18f39a6480a56b26cf72e344f4fe6749e48df6"}, "shortDescription": "UTA-Model-Deploymentment-Module", "title": "Streamlit Frontend Churn", "isLikedByUser": false, "trendingScore": 0, "tags": ["docker", "streamlit", "region:us"], "featured": false}], "numItemsPerPage": 24, "numTotalItems": 1050922, "pageIndex": 0}